jitx/__init__.py
jitx/__main__.py
jitx/_instantiation.py
jitx/_structural.py
jitx/_websocket.py
jitx/anchor.py
jitx/board.py
jitx/circuit.py
jitx/common.py
jitx/component.py
jitx/constraints.py
jitx/container.py
jitx/context.py
jitx/copper.py
jitx/decorators.py
jitx/design.py
jitx/error.py
jitx/events.py
jitx/feature.py
jitx/fileinfo.py
jitx/inspect.py
jitx/interval.py
jitx/landpattern.py
jitx/layerindex.py
jitx/logo.py
jitx/memo.py
jitx/model3d.py
jitx/net.py
jitx/paper.py
jitx/placement.py
jitx/property.py
jitx/refpath.py
jitx/schematic.py
jitx/si.py
jitx/stackup.py
jitx/substrate.py
jitx/symbol.py
jitx/test.py
jitx/toleranced.py
jitx/transform.py
jitx/units.py
jitx/via.py
jitx/_translate/board.py
jitx/_translate/bundle.py
jitx/_translate/circuit.py
jitx/_translate/component.py
jitx/_translate/copper.py
jitx/_translate/design.py
jitx/_translate/dispatch.py
jitx/_translate/enums.py
jitx/_translate/feature.py
jitx/_translate/fileinfo.py
jitx/_translate/idmap.py
jitx/_translate/landpattern.py
jitx/_translate/layerindex.py
jitx/_translate/mapping.py
jitx/_translate/routing.py
jitx/_translate/rules.py
jitx/_translate/schematic.py
jitx/_translate/shape.py
jitx/_translate/signal_models.py
jitx/_translate/symbol.py
jitx/_translate/via.py
jitx/compat/__init__.py
jitx/compat/altium.py
jitx/run/__init__.py
jitx/run/dependencies.py
jitx/run/pyproject.py
jitx/sample/__init__.py
jitx/shapes/__init__.py
jitx/shapes/composites.py
jitx/shapes/primitive.py
jitx/shapes/shapely.py
jitx/vscode/__init__.py
jitx/vscode/config.py
jitx-4.0.3.dist-info/METADATA
jitx-4.0.3.dist-info/WHEEL
jitx-4.0.3.dist-info/RECORD
