Metadata-Version: 2.4
Name: jitx
Version: 4.0.3
Summary: Design complex circuit boards by writing simple code and streamline your existing design process
Project-URL: Homepage, https://jitx.com
Project-URL: Documentation, https://docs.jitx.com
Author: JITX
Maintainer: JITX
Keywords: circuit board,jitx,pcb
Classifier: Development Status :: 1 - Planning
Classifier: Framework :: Hatch
Classifier: Framework :: Pytest
Classifier: Intended Audience :: Developers
Classifier: License :: Other/Proprietary License
Classifier: Operating System :: MacOS :: MacOS X
Classifier: Operating System :: Microsoft :: Windows :: Windows 10
Classifier: Operating System :: Microsoft :: Windows :: Windows 11
Classifier: Operating System :: POSIX :: Linux
Classifier: Programming Language :: Python
Classifier: Programming Language :: Python :: 3 :: Only
Classifier: Programming Language :: Python :: 3.12
Classifier: Programming Language :: Python :: 3.13
Classifier: Topic :: Scientific/Engineering :: Electronic Design Automation (EDA)
Classifier: Topic :: Software Development :: Libraries :: Python Modules
Classifier: Typing :: Typed
Requires-Python: >=3.12
Requires-Dist: jitxcore==4.0.0
Requires-Dist: packaging<26.0,>=25.0
Requires-Dist: pint==0.24.4
Requires-Dist: shapely<3.0,>=2.1.0
Requires-Dist: websockets==15.0.1
